odoo/addons/account_cash_discount_base_sale/README.rst
odoo/addons/account_cash_discount_base_sale/__init__.py
odoo/addons/account_cash_discount_base_sale/__manifest__.py
odoo/addons/account_cash_discount_base_sale/i18n/account_cash_discount_base_sale.pot
odoo/addons/account_cash_discount_base_sale/models/__init__.py
odoo/addons/account_cash_discount_base_sale/models/account_move.py
odoo/addons/account_cash_discount_base_sale/models/sale_order.py
odoo/addons/account_cash_discount_base_sale/readme/CONTRIBUTORS.rst
odoo/addons/account_cash_discount_base_sale/readme/DESCRIPTION.rst
odoo/addons/account_cash_discount_base_sale/static/description/icon.png
odoo/addons/account_cash_discount_base_sale/static/description/index.html
odoo/addons/account_cash_discount_base_sale/tests/__init__.py
odoo/addons/account_cash_discount_base_sale/tests/test_account_cash_discount_base_sale.py
odoo13_addon_account_cash_discount_base_sale-13.0.1.0.1.dev3.dist-info/METADATA
odoo13_addon_account_cash_discount_base_sale-13.0.1.0.1.dev3.dist-info/WHEEL
odoo13_addon_account_cash_discount_base_sale-13.0.1.0.1.dev3.dist-info/top_level.txt
odoo13_addon_account_cash_discount_base_sale-13.0.1.0.1.dev3.dist-info/RECORD
