Metadata-Version: 2.1
Name: odoo13-addon-account-cash-discount-base-sale
Version: 13.0.1.0.1.dev3
Summary: Glue module between account_cash_discount_base and standard sale addon.
Home-page: https://github.com/OCA/account-payment
Author: ACSONE SA/NV,Odoo Community Association (OCA)
Author-email: support@odoo-community.org
License: AGPL-3
Platform: UNKNOWN
Classifier: Programming Language :: Python
Classifier: Framework :: Odoo
Classifier: Framework :: Odoo :: 13.0
Classifier: License :: OSI Approved :: GNU Affero General Public License v3
Requires-Python: >=3.5
Requires-Dist: odoo13-addon-account-cash-discount-base
Requires-Dist: odoo <13.1dev,>=13.0a
